{
  "url": "https://iesjuandelanuza.catedu.es/?p=331",
  "title": "Cómo funciona SIGAD – IES Juan de Lanuza",
  "depth": 4,
  "parentUrl": "https://iesjuandelanuza.catedu.es/manuales-de-sigad/",
  "domain": "iesjuandelanuza.catedu.es",
  "timestamp": "2026-04-18T15:55:53.719Z",
  "statusCode": 200,
  "contentType": "text/html; charset=UTF-8",
  "pageId": "1d6c017534d5248dc170be546f11e077",
  "screenshotPath": "pages/screenshots/1d6c017534d5248dc170be546f11e077.png",
  "htmlPath": "pages/html/1d6c017534d5248dc170be546f11e077.html"
}