{
  "url": "https://iesjuandelanuza.catedu.es/formacion-y-orientacion-laboral/",
  "title": "Formación y Orientación Laboral – IES Juan de Lanuza",
  "depth": 2,
  "parentUrl": "https://iesjuandelanuza.catedu.es",
  "domain": "iesjuandelanuza.catedu.es",
  "timestamp": "2026-04-18T15:54:07.464Z",
  "statusCode": 200,
  "contentType": "text/html; charset=UTF-8",
  "pageId": "4c2e22e000125de279ecd71db2b9f159",
  "screenshotPath": "pages/screenshots/4c2e22e000125de279ecd71db2b9f159.png",
  "htmlPath": "pages/html/4c2e22e000125de279ecd71db2b9f159.html"
}