{
  "url": "https://iesjuandelanuza.catedu.es/?p=4085",
  "title": "Consejo Escolar – IES Juan de Lanuza",
  "depth": 4,
  "parentUrl": "https://iesjuandelanuza.catedu.es/consejo-escolar-2/",
  "domain": "iesjuandelanuza.catedu.es",
  "timestamp": "2026-04-18T15:55:30.868Z",
  "statusCode": 200,
  "contentType": "text/html; charset=UTF-8",
  "pageId": "63b2e2eafeedf71ab1341c03093a6729",
  "screenshotPath": "pages/screenshots/63b2e2eafeedf71ab1341c03093a6729.png",
  "htmlPath": "pages/html/63b2e2eafeedf71ab1341c03093a6729.html"
}