{
  "url": "http://iesjuandelanuza.catedu.es/hosteleria/",
  "title": "Hostelería y Turismo – IES Juan de Lanuza",
  "depth": 2,
  "parentUrl": "https://iesjuandelanuza.catedu.es",
  "domain": "iesjuandelanuza.catedu.es",
  "timestamp": "2026-04-18T15:54:53.688Z",
  "statusCode": 200,
  "contentType": "text/html; charset=UTF-8",
  "pageId": "8116c5a8c3a09b1c412f3dd9908d086d",
  "screenshotPath": "pages/screenshots/8116c5a8c3a09b1c412f3dd9908d086d.png",
  "htmlPath": "pages/html/8116c5a8c3a09b1c412f3dd9908d086d.html"
}