{
  "url": "https://iesjuandelanuza.catedu.es/wp-json/wp/v2/pages/2097",
  "title": "",
  "depth": 4,
  "parentUrl": "https://iesjuandelanuza.catedu.es/comienzo-de-curso-profesores/",
  "domain": "iesjuandelanuza.catedu.es",
  "timestamp": "2026-04-18T15:56:25.301Z",
  "statusCode": 200,
  "contentType": "application/json; charset=UTF-8",
  "pageId": "85c66446bd7199b2504e30384cd78670",
  "screenshotPath": "pages/screenshots/85c66446bd7199b2504e30384cd78670.png",
  "htmlPath": "pages/html/85c66446bd7199b2504e30384cd78670.html"
}